pyrtz2/__init__.py
pyrtz2/afm.py
pyrtz2/app.py
pyrtz2/asylum.py
pyrtz2/curves.py
pyrtz2/fit.py
pyrtz2/assets/style.css
pyrtz2/src/__init__.py
pyrtz2/src/components/__init__.py
pyrtz2/src/components/annotator.py
pyrtz2/src/components/contact_controls.py
pyrtz2/src/components/curve_dropdown.py
pyrtz2/src/components/downloader.py
pyrtz2/src/components/experiment_loader.py
pyrtz2/src/components/fig.py
pyrtz2/src/components/fig_frame.py
pyrtz2/src/components/fitter.py
pyrtz2/src/components/ids.py
pyrtz2/src/components/image.py
pyrtz2/src/components/image_controls.py
pyrtz2/src/components/image_frame.py
pyrtz2/src/components/image_loader.py
pyrtz2/src/components/layout.py
pyrtz2/src/components/loader.py
pyrtz2/src/components/toolbox.py
pyrtz2/src/utils/__init__.py
pyrtz2/src/utils/processor.py
pyrtz2/src/utils/utils.py
pyrtz2-1.4.8.dist-info/METADATA
pyrtz2-1.4.8.dist-info/WHEEL
pyrtz2-1.4.8.dist-info/licenses/LICENSE
pyrtz2-1.4.8.dist-info/RECORD
