Metadata-Version: 2.4
Name: pyrtz2
Version: 1.4.8
Summary: Automated analysis of AFM force curves and images via Python.
Project-URL: documentation, https://www.youtube.com/@hoseynamiri
Project-URL: repository, https://github.com/HoseynAAmiri/pyrtz2
Project-URL: homepage, https://github.com/HoseynAAmiri
Author-email: "Hoseyn A. Amiri" <aamirihoseyn@gmail.com>
License: MIT License
License-File: LICENSE
Requires-Python: >=3.11
Requires-Dist: dash-bootstrap-components>=1.6.0
Requires-Dist: dash>=3.1.1
Requires-Dist: igor2>=0.5.9
Requires-Dist: kaleido>=1.0.0
Requires-Dist: opencv-python>=4.10.0.84
Requires-Dist: pandas>=2.2.3
Requires-Dist: pypdf2>=3.0.1
Requires-Dist: scikit-image>=0.25.2
Requires-Dist: scikit-learn>=1.5.0
Requires-Dist: scipy>=1.15.1
Requires-Dist: tqdm>=4.67.1
